{
  "project_info": {
    "project_number": "791661209203",
    "project_id": "omniwatch-ed70b",
    "storage_bucket": "omniwatch-ed70b.firebasestorage.app"
  },
  "client": [
    {
      "client_info": {
        "mobilesdk_app_id": "1:791661209203:android:4755699d10fb1f22cc2c06",
        "android_client_info": {
          "package_name": "com.hustlerati.buildonbudget"
        }
      },
      "oauth_client": [],
      "api_key": [
        {
          "current_key": "AIzaSyDx7WNczW87OszNmhk6oVo1cZWXp0rXNZM"
        }
      ],
      "services": {
        "appinvite_service": {
          "other_platform_oauth_client": []
        }
      }
    },
    {
      "client_info": {
        "mobilesdk_app_id": "1:791661209203:android:403be80cdea1f438cc2c06",
        "android_client_info": {
          "package_name": "com.hustlerati.patrollink"
        }
      },
      "oauth_client": [],
      "api_key": [
        {
          "current_key": "AIzaSyDx7WNczW87OszNmhk6oVo1cZWXp0rXNZM"
        }
      ],
      "services": {
        "appinvite_service": {
          "other_platform_oauth_client": []
        }
      }
    }
  ],
  "configuration_version": "1"
}